rgevolve/smeft/warsaw_up/__init__.py
rgevolve/smeft/warsaw_up/_version.py
rgevolve/smeft/warsaw_up/data.h5
rgevolve_smeft_warsaw_up-0.1.1.dist-info/licenses/LICENSE
rgevolve_smeft_warsaw_up-0.1.1.dist-info/METADATA
rgevolve_smeft_warsaw_up-0.1.1.dist-info/WHEEL
rgevolve_smeft_warsaw_up-0.1.1.dist-info/top_level.txt
rgevolve_smeft_warsaw_up-0.1.1.dist-info/RECORD
