Metadata-Version: 2.4
Name: rgevolve.smeft.warsaw_up
Version: 0.1.1
Summary: Package providing Renormalization Group Evolution Matrices for the SMEFT in the "Warsaw up" basis
Author-email: Aleks Smolkovič <aleks.smolkovic@ijs.si>, Peter Stangl <peter.stangl@cern.ch>
License: MIT
Requires-Python: >=3.8
License-File: LICENSE
Requires-Dist: rgevolve-core
Dynamic: license-file
